explicit_nlu/ExplicitEngine.py
explicit_nlu/__init__.py
explicit_nlu/__test__/__init__.py
explicit_nlu/__test__/extractors.xml
explicit_nlu/__test__/test_explicit_engine.py
explicit_nlu/antlr/ECL.interp
explicit_nlu/antlr/ECL.tokens
explicit_nlu/antlr/ECLLexer.interp
explicit_nlu/antlr/ECLLexer.py
explicit_nlu/antlr/ECLLexer.tokens
explicit_nlu/antlr/ECLListener.py
explicit_nlu/antlr/ECLParser.py
explicit_nlu/antlr/ECLVisitor.py
explicit_nlu/antlr/EQL.interp
explicit_nlu/antlr/EQL.tokens
explicit_nlu/antlr/EQLLexer.interp
explicit_nlu/antlr/EQLLexer.py
explicit_nlu/antlr/EQLLexer.tokens
explicit_nlu/antlr/EQLListener.py
explicit_nlu/antlr/EQLParser.py
explicit_nlu/antlr/EQLVisitor.py
explicit_nlu/api/IConversion.py
explicit_nlu/api/IConversionBinding.py
explicit_nlu/api/IToken.py
explicit_nlu/api/Navigator.py
explicit_nlu/api/__init__.py
explicit_nlu/api/support/Strings.py
explicit_nlu/evaluator/ExplicitEvaluation.py
explicit_nlu/evaluator/ExplicitEvaluator.py
explicit_nlu/evaluator/__init__.py
explicit_nlu/extractor/BooleanExtractor.py
explicit_nlu/extractor/FunctionExtractor.py
explicit_nlu/extractor/NumberExtractor.py
explicit_nlu/extractor/StringExtractor.py
explicit_nlu/extractor/VariableExtractor.py
explicit_nlu/extractor/__init__.py
explicit_nlu/extractor/binding/ExplicitConversionBinding.py
explicit_nlu/extractor/binding/__init__.py
explicit_nlu/listener/ExplicitRulesErrorListener.py
explicit_nlu/listener/__init__.py
explicit_nlu/parser/AntlrParser.py
explicit_nlu/parser/ExplicitRule.py
explicit_nlu/parser/ExplicitRules.py
explicit_nlu/parser/__init__.py
explicit_nlu/parser/xml/ExplicitXmlParser.py
explicit_nlu/parser/xml/__init__.py
explicit_nlu/parser/xml/__test__/XmlExplicitRulesParserTest.py
explicit_nlu/parser/xml/__test__/__init__.py
explicit_nlu/token/Alias.py
explicit_nlu/token/Atomic.py
explicit_nlu/token/Escaped.py
explicit_nlu/token/Group.py
explicit_nlu/token/Label.py
explicit_nlu/token/Like.py
explicit_nlu/token/Not.py
explicit_nlu-0.10.6.dist-info/entry_points.txt
explicit_nlu-0.10.6.dist-info/WHEEL
explicit_nlu-0.10.6.dist-info/METADATA
explicit_nlu-0.10.6.dist-info/RECORD
