Metadata-Version: 2.1
Name: explicit-nlu
Version: 0.10.6
Summary: Explicit is a cross platform library for rule based named entity recognition.
Author: Leftshift One
Author-email: contact@leftshift.one
Requires-Python: >=3.7,<4.0
Classifier: Programming Language :: Python :: 3
Classifier: Programming Language :: Python :: 3.7
Classifier: Programming Language :: Python :: 3.8
Requires-Dist: antlr4-python3-runtime (>=4.8,<5.0)
